[{"date":"2021-05-06","heure":"09:08","localisation":"dfqsqsdfqs","degat":"non","blesse":"non"},["Il n'y a pas de t\u00e9moin"],{"nom":"Baucor","prenom":"Victor","adresse":"16 chemin lous toupis, 64230,, France","telephone":"0770361970","email":"baucor.victor@gmail.com","marque":"Peugeot 307","immatriculation":"65456","paysImm":"fqsd","remorque":"non","assurance":"GAN","numContrat":"122131435614","numCarteVerte":"qsdf","dateValidite":"2021-06-02","agence":"qsdf","degatMateriel":"oui","numeroPermis":"qszef","Categorie":"qaez","datePermis":"2021-05-13","Circonstance":"Changeait de file","degatsApparents":"f","Observations":"f"},{"nom":"sdf","prenom":"skjdgsfkh","adresse":"kjhsd;khfkjsh,kjxckvf,,kjbsdkfjhdqskjh","telephone":"hkjsdhf","email":"s@sq","marque":"dsfqsdf","immatriculation":"dwsxf","paysImm":"cdfsf","remorque":"non","assurance":"sdf","numContrat":"fdss","numCarteVerte":"dfs","dateValidite":"2021-05-20","agence":"sdf","degatMateriel":"oui","numeroPermis":"kdfjq","Categorie":"lkjdqsf","datePermis":"2021-05-20","Circonstance":"Heurtait \u00e0 l'arri\u00e8re, en roulant dans le m\u00eame sens et sur une m\u00eame file","degatsApparents":"f","Observations":"f"}]